{"chunk_definitions":[{"chunk_id":"cwu3s5r32bbcl","chunk_label":"Library","document_id":"B8643DDD","expansion_state":0,"options":{"engine":"r","label":"Library"},"row":16,"row_count":1,"visible":true},{"chunk_id":"ckuyyisa20npn","chunk_label":"Ingest Raw Text","document_id":"B8643DDD","expansion_state":0,"options":{"engine":"r","label":"Ingest Raw Text"},"row":31,"row_count":1,"visible":true},{"chunk_id":"cy4t9drg7cu6r","chunk_label":"Pre-processing","document_id":"B8643DDD","expansion_state":0,"options":{"engine":"r","label":"Pre-processing"},"row":45,"row_count":1,"visible":true},{"chunk_id":"crc1xnjymzyph","chunk_label":"Remove Infrequent Words","document_id":"B8643DDD","expansion_state":0,"options":{"engine":"r","label":"Remove Infrequent Words"},"row":74,"row_count":1,"visible":true},{"chunk_id":"ci8yi83bz93f3","chunk_label":"Covariate - P5","document_id":"B8643DDD","expansion_state":0,"options":{"engine":"r","label":"Covariate - P5"},"row":90,"row_count":1,"visible":true},{"chunk_id":"cas7431wy1fpc","chunk_label":"Covariate - NWS","document_id":"B8643DDD","expansion_state":0,"options":{"engine":"r","label":"Covariate - NWS"},"row":114,"row_count":1,"visible":true},{"chunk_id":"cgnd14r9cpqrr","chunk_label":"Covariate ECOWAS","document_id":"B8643DDD","expansion_state":0,"options":{"engine":"r","label":"Covariate ECOWAS"},"row":143,"row_count":1,"visible":true}],"chunk_rendered_width":700,"doc_write_time":1587410554}